Incident.py
generate.py
tmrevpviz.py
tmrevpviz-1.3.1.dist-info/LICENSE
tmrevpviz-1.3.1.dist-info/METADATA
tmrevpviz-1.3.1.dist-info/WHEEL
tmrevpviz-1.3.1.dist-info/entry_points.txt
tmrevpviz-1.3.1.dist-info/top_level.txt
tmrevpviz-1.3.1.dist-info/RECORD
