Metadata-Version: 2.1
Name: tmrevpviz
Version: 1.3.1
Summary: UNKNOWN
Home-page: UNKNOWN
Author: UNKNOWN
Author-email: UNKNOWN
License: MIT
Platform: UNKNOWN
Classifier: Environment :: Console
Classifier: Operating System :: Microsoft :: Windows
Classifier: Programming Language :: Python
Requires-Dist: datetime
Requires-Dist: matplotlib
Requires-Dist: numpy
Requires-Dist: pandas
Requires-Dist: statistics
Requires-Dist: xlsxwriter
Requires-Dist: xlrd
